<?xml version="1.0" encoding="UTF-8" standalone="yes"?><ns2:GridDefinitionFileOutputV2 xmlns:ns2="http://www.gtech.com/xml/eInstants/base/common/CatAdminV1"><GridBody><GridProperties><Version>19</Version><GameType>0</GameType><GridSize>1000000</GridSize><RevFileSig>Ewfb9RuUMzshArxonkkkSPiUI5IH30c62uaR4FBsbJAR7MA3Qu9MUrC3F5AD2aTXQr9T9A+q8liGgbkGq+Q0Pg==</RevFileSig><BigEndianFlg>false</BigEndianFlg><SiteID>94</SiteID><PricePoint>3000</PricePoint><BetUnits>1</BetUnits><ValidationUnits>1</ValidationUnits><NoOfDivisions>81</NoOfDivisions><LongName>KNM Bonus 2</LongName><ShortName>KMB02</ShortName><GridMethod>3</GridMethod><GridTrigger>0</GridTrigger><GridTriggerUnit>0</GridTriggerUnit><VendorID>1</VendorID><IntAuditVendorID>2</IntAuditVendorID><ExtAuditVendorID>0</ExtAuditVendorID><DeliveryChannel>3</DeliveryChannel><Jackpot>false</Jackpot></GridProperties><DivisionRow><Winners>1</Winners><WinAmt>60000000</WinAmt><PrizeTableAmt>60000000</PrizeTableAmt><PrizeType>0</PrizeType></DivisionRow><DivisionRow><Winners>2</Winners><WinAmt>3000000</WinAmt><PrizeTableAmt>900000</PrizeTableAmt><PrizeType>0</PrizeType></DivisionRow><DivisionRow><Winners>1</Winners><WinAmt>2850000</WinAmt><PrizeTableAmt>150000</PrizeTableAmt><PrizeType>0</PrizeType></DivisionRow><DivisionRow><Winners>1</Winners><WinAmt>2775000</WinAmt><PrizeTableAmt>60000</PrizeTableAmt><PrizeType>0</PrizeType></DivisionRow><DivisionRow><Winners>1</Winners><WinAmt>2700000</WinAmt><PrizeTableAmt>30000</PrizeTableAmt><PrizeType>0</PrizeType></DivisionRow><DivisionRow><Winners>1</Winners><WinAmt>1920000</WinAmt><PrizeTableAmt>15000</PrizeTableAmt><PrizeType>0</PrizeType></DivisionRow><DivisionRow><Winners>1</Winners><WinAmt>1920000</WinAmt><PrizeTableAmt>12000</PrizeTableAmt><PrizeType>0</PrizeType></DivisionRow><DivisionRow><Winners>1</Winners><WinAmt>1890000</WinAmt><PrizeTableAmt>9000</PrizeTableAmt><PrizeType>0</PrizeType></DivisionRow><DivisionRow><Winners>1</Winners><WinAmt>1890000</WinAmt><PrizeTableAmt>6000</PrizeTableAmt><PrizeType>0</PrizeType></DivisionRow><DivisionRow><Winners>1</Winners><WinAmt>1875000</WinAmt><PrizeTableAmt>3000</PrizeTableAmt><PrizeType>0</PrizeType></DivisionRow><DivisionRow><Winners>1</Winners><WinAmt>1875000</WinAmt><PrizeTableAmt>60000</PrizeTableAmt><PrizeType>0</PrizeType></DivisionRow><DivisionRow><Winners>1</Winners><WinAmt>1860000</WinAmt><PrizeTableAmt>45000</PrizeTableAmt><PrizeType>0</PrizeType></DivisionRow><DivisionRow><Winners>1</Winners><WinAmt>1860000</WinAmt><PrizeTableAmt>30000</PrizeTableAmt><PrizeType>0</PrizeType></DivisionRow><DivisionRow><Winners>1</Winners><WinAmt>1830000</WinAmt><PrizeTableAmt>24000</PrizeTableAmt><PrizeType>0</PrizeType></DivisionRow><DivisionRow><Winners>1</Winners><WinAmt>1830000</WinAmt><PrizeTableAmt>18000</PrizeTableAmt><PrizeType>0</PrizeType></DivisionRow><DivisionRow><Winners>2</Winners><WinAmt>1800000</WinAmt><PrizeTableAmt>15000</PrizeTableAmt><PrizeType>0</PrizeType></DivisionRow><DivisionRow><Winners>1</Winners><WinAmt>1050000</WinAmt><PrizeTableAmt>12000</PrizeTableAmt><PrizeType>0</PrizeType></DivisionRow><DivisionRow><Winners>1</Winners><WinAmt>1050000</WinAmt><PrizeTableAmt>10500</PrizeTableAmt><PrizeType>0</PrizeType></DivisionRow><DivisionRow><Winners>1</Winners><WinAmt>990000</WinAmt><PrizeTableAmt>9000</PrizeTableAmt><PrizeType>0</PrizeType></DivisionRow><DivisionRow><Winners>1</Winners><WinAmt>990000</WinAmt><PrizeTableAmt>7500</PrizeTableAmt><PrizeType>0</PrizeType></DivisionRow><DivisionRow><Winners>1</Winners><WinAmt>975000</WinAmt><PrizeTableAmt>6000</PrizeTableAmt><PrizeType>0</PrizeType></DivisionRow><DivisionRow><Winners>1</Winners><WinAmt>975000</WinAmt><PrizeTableAmt>4500</PrizeTableAmt><PrizeType>0</PrizeType></DivisionRow><DivisionRow><Winners>1</Winners><WinAmt>960000</WinAmt><PrizeTableAmt>3000</PrizeTableAmt><PrizeType>0</PrizeType></DivisionRow><DivisionRow><Winners>1</Winners><WinAmt>960000</WinAmt><PrizeTableAmt>1500</PrizeTableAmt><PrizeType>0</PrizeType></DivisionRow><DivisionRow><Winners>1</Winners><WinAmt>930000</WinAmt><PrizeTableAmt>150000</PrizeTableAmt><PrizeType>0</PrizeType></DivisionRow><DivisionRow><Winners>1</Winners><WinAmt>930000</WinAmt><PrizeTableAmt>60000</PrizeTableAmt><PrizeType>0</PrizeType></DivisionRow><DivisionRow><Winners>10</Winners><WinAmt>900000</WinAmt><PrizeTableAmt>30000</PrizeTableAmt><PrizeType>0</PrizeType></DivisionRow><DivisionRow><Winners>150</Winners><WinAmt>150000</WinAmt><PrizeTableAmt>15000</PrizeTableAmt><PrizeType>0</PrizeType></DivisionRow><DivisionRow><Winners>150</Winners><WinAmt>150000</WinAmt><PrizeTableAmt>12000</PrizeTableAmt><PrizeType>0</PrizeType></DivisionRow><DivisionRow><Winners>50</Winners><WinAmt>135000</WinAmt><PrizeTableAmt>9000</PrizeTableAmt><PrizeType>0</PrizeType></DivisionRow><DivisionRow><Winners>50</Winners><WinAmt>135000</WinAmt><PrizeTableAmt>6000</PrizeTableAmt><PrizeType>0</PrizeType></DivisionRow><DivisionRow><Winners>200</Winners><WinAmt>120000</WinAmt><PrizeTableAmt>3000</PrizeTableAmt><PrizeType>0</PrizeType></DivisionRow><DivisionRow><Winners>200</Winners><WinAmt>120000</WinAmt><PrizeTableAmt>0</PrizeTableAmt><PrizeType>0</PrizeType></DivisionRow><DivisionRow><Winners>100</Winners><WinAmt>105000</WinAmt><PrizeTableAmt>0</PrizeTableAmt><PrizeType>0</PrizeType></DivisionRow><DivisionRow><Winners>100</Winners><WinAmt>105000</WinAmt><PrizeTableAmt>0</PrizeTableAmt><PrizeType>0</PrizeType></DivisionRow><DivisionRow><Winners>250</Winners><WinAmt>90000</WinAmt><PrizeTableAmt>0</PrizeTableAmt><PrizeType>0</PrizeType></DivisionRow><DivisionRow><Winners>250</Winners><WinAmt>90000</WinAmt><PrizeTableAmt>0</PrizeTableAmt><PrizeType>0</PrizeType></DivisionRow><DivisionRow><Winners>50</Winners><WinAmt>82500</WinAmt><PrizeTableAmt>0</PrizeTableAmt><PrizeType>0</PrizeType></DivisionRow><DivisionRow><Winners>50</Winners><WinAmt>75000</WinAmt><PrizeTableAmt>0</PrizeTableAmt><PrizeType>0</PrizeType></DivisionRow><DivisionRow><Winners>300</Winners><WinAmt>75000</WinAmt><PrizeTableAmt>0</PrizeTableAmt><PrizeType>0</PrizeType></DivisionRow><DivisionRow><Winners>150</Winners><WinAmt>67500</WinAmt><PrizeTableAmt>0</PrizeTableAmt><PrizeType>0</PrizeType></DivisionRow><DivisionRow><Winners>750</Winners><WinAmt>60000</WinAmt><PrizeTableAmt>0</PrizeTableAmt><PrizeType>0</PrizeType></DivisionRow><DivisionRow><Winners>750</Winners><WinAmt>60000</WinAmt><PrizeTableAmt>0</PrizeTableAmt><PrizeType>0</PrizeType></DivisionRow><DivisionRow><Winners>200</Winners><WinAmt>52500</WinAmt><PrizeTableAmt>0</PrizeTableAmt><PrizeType>0</PrizeType></DivisionRow><DivisionRow><Winners>200</Winners><WinAmt>48000</WinAmt><PrizeTableAmt>0</PrizeTableAmt><PrizeType>0</PrizeType></DivisionRow><DivisionRow><Winners>500</Winners><WinAmt>48000</WinAmt><PrizeTableAmt>0</PrizeTableAmt><PrizeType>0</PrizeType></DivisionRow><DivisionRow><Winners>700</Winners><WinAmt>45000</WinAmt><PrizeTableAmt>0</PrizeTableAmt><PrizeType>0</PrizeType></DivisionRow><DivisionRow><Winners>700</Winners><WinAmt>45000</WinAmt><PrizeTableAmt>0</PrizeTableAmt><PrizeType>0</PrizeType></DivisionRow><DivisionRow><Winners>500</Winners><WinAmt>37500</WinAmt><PrizeTableAmt>0</PrizeTableAmt><PrizeType>0</PrizeType></DivisionRow><DivisionRow><Winners>1500</Winners><WinAmt>36000</WinAmt><PrizeTableAmt>0</PrizeTableAmt><PrizeType>0</PrizeType></DivisionRow><DivisionRow><Winners>1500</Winners><WinAmt>36000</WinAmt><PrizeTableAmt>0</PrizeTableAmt><PrizeType>0</PrizeType></DivisionRow><DivisionRow><Winners>400</Winners><WinAmt>30000</WinAmt><PrizeTableAmt>0</PrizeTableAmt><PrizeType>0</PrizeType></DivisionRow><DivisionRow><Winners>400</Winners><WinAmt>30000</WinAmt><PrizeTableAmt>0</PrizeTableAmt><PrizeType>0</PrizeType></DivisionRow><DivisionRow><Winners>300</Winners><WinAmt>28500</WinAmt><PrizeTableAmt>0</PrizeTableAmt><PrizeType>0</PrizeType></DivisionRow><DivisionRow><Winners>600</Winners><WinAmt>27000</WinAmt><PrizeTableAmt>0</PrizeTableAmt><PrizeType>0</PrizeType></DivisionRow><DivisionRow><Winners>600</Winners><WinAmt>27000</WinAmt><PrizeTableAmt>0</PrizeTableAmt><PrizeType>0</PrizeType></DivisionRow><DivisionRow><Winners>400</Winners><WinAmt>25500</WinAmt><PrizeTableAmt>0</PrizeTableAmt><PrizeType>0</PrizeType></DivisionRow><DivisionRow><Winners>800</Winners><WinAmt>24000</WinAmt><PrizeTableAmt>0</PrizeTableAmt><PrizeType>0</PrizeType></DivisionRow><DivisionRow><Winners>800</Winners><WinAmt>24000</WinAmt><PrizeTableAmt>0</PrizeTableAmt><PrizeType>0</PrizeType></DivisionRow><DivisionRow><Winners>900</Winners><WinAmt>22500</WinAmt><PrizeTableAmt>0</PrizeTableAmt><PrizeType>0</PrizeType></DivisionRow><DivisionRow><Winners>1000</Winners><WinAmt>21000</WinAmt><PrizeTableAmt>0</PrizeTableAmt><PrizeType>0</PrizeType></DivisionRow><DivisionRow><Winners>1000</Winners><WinAmt>21000</WinAmt><PrizeTableAmt>0</PrizeTableAmt><PrizeType>0</PrizeType></DivisionRow><DivisionRow><Winners>1500</Winners><WinAmt>19500</WinAmt><PrizeTableAmt>0</PrizeTableAmt><PrizeType>0</PrizeType></DivisionRow><DivisionRow><Winners>1750</Winners><WinAmt>18000</WinAmt><PrizeTableAmt>0</PrizeTableAmt><PrizeType>0</PrizeType></DivisionRow><DivisionRow><Winners>1750</Winners><WinAmt>18000</WinAmt><PrizeTableAmt>0</PrizeTableAmt><PrizeType>0</PrizeType></DivisionRow><DivisionRow><Winners>2000</Winners><WinAmt>16500</WinAmt><PrizeTableAmt>0</PrizeTableAmt><PrizeType>0</PrizeType></DivisionRow><DivisionRow><Winners>1000</Winners><WinAmt>15000</WinAmt><PrizeTableAmt>0</PrizeTableAmt><PrizeType>0</PrizeType></DivisionRow><DivisionRow><Winners>1000</Winners><WinAmt>15000</WinAmt><PrizeTableAmt>0</PrizeTableAmt><PrizeType>0</PrizeType></DivisionRow><DivisionRow><Winners>1500</Winners><WinAmt>13500</WinAmt><PrizeTableAmt>0</PrizeTableAmt><PrizeType>0</PrizeType></DivisionRow><DivisionRow><Winners>2000</Winners><WinAmt>12000</WinAmt><PrizeTableAmt>0</PrizeTableAmt><PrizeType>0</PrizeType></DivisionRow><DivisionRow><Winners>2000</Winners><WinAmt>12000</WinAmt><PrizeTableAmt>0</PrizeTableAmt><PrizeType>0</PrizeType></DivisionRow><DivisionRow><Winners>3000</Winners><WinAmt>10500</WinAmt><PrizeTableAmt>0</PrizeTableAmt><PrizeType>0</PrizeType></DivisionRow><DivisionRow><Winners>4000</Winners><WinAmt>9000</WinAmt><PrizeTableAmt>0</PrizeTableAmt><PrizeType>0</PrizeType></DivisionRow><DivisionRow><Winners>4000</Winners><WinAmt>9000</WinAmt><PrizeTableAmt>0</PrizeTableAmt><PrizeType>0</PrizeType></DivisionRow><DivisionRow><Winners>6000</Winners><WinAmt>7500</WinAmt><PrizeTableAmt>0</PrizeTableAmt><PrizeType>0</PrizeType></DivisionRow><DivisionRow><Winners>9000</Winners><WinAmt>6000</WinAmt><PrizeTableAmt>0</PrizeTableAmt><PrizeType>0</PrizeType></DivisionRow><DivisionRow><Winners>9000</Winners><WinAmt>6000</WinAmt><PrizeTableAmt>0</PrizeTableAmt><PrizeType>0</PrizeType></DivisionRow><DivisionRow><Winners>60086</Winners><WinAmt>4500</WinAmt><PrizeTableAmt>0</PrizeTableAmt><PrizeType>0</PrizeType></DivisionRow><DivisionRow><Winners>61913</Winners><WinAmt>3000</WinAmt><PrizeTableAmt>0</PrizeTableAmt><PrizeType>0</PrizeType></DivisionRow><DivisionRow><Winners>61913</Winners><WinAmt>3000</WinAmt><PrizeTableAmt>0</PrizeTableAmt><PrizeType>0</PrizeType></DivisionRow><DivisionRow><Winners>750000</Winners><WinAmt>0</WinAmt><PrizeTableAmt>0</PrizeTableAmt><PrizeType>0</PrizeType></DivisionRow><GridRefill/></GridBody><GridFooter><checksum enc="hex">9C4942B7A02B909DAD7687B16AD439903ED365524962C307C1B310E9E8C4DB3F</checksum></GridFooter></ns2:GridDefinitionFileOutputV2>